npm_vuln_scanner/__init__.py
npm_vuln_scanner/__main__.py
npm_vuln_scanner/checker.py
npm_vuln_scanner/cli.py
npm_vuln_scanner/scanner.py
npm_vuln_scanner/utils.py
npm_vuln_scanner-1.2.0.dist-info/licenses/LICENSE
npm_vuln_scanner-1.2.0.dist-info/METADATA
npm_vuln_scanner-1.2.0.dist-info/WHEEL
npm_vuln_scanner-1.2.0.dist-info/entry_points.txt
npm_vuln_scanner-1.2.0.dist-info/top_level.txt
npm_vuln_scanner-1.2.0.dist-info/RECORD
