Metadata-Version: 2.4
Name: npm-vuln-scanner
Version: 1.2.0
Summary: Detect compromised npm packages from the September 2025 supply chain attack
Author-email: Michael Bommarito <michael.bommarito@gmail.com>
License-Expression: MIT
Project-URL: Homepage, https://github.com/mjbommar/npm-vuln-scanner
Project-URL: Documentation, https://github.com/mjbommar/npm-vuln-scanner#readme
Project-URL: Repository, https://github.com/mjbommar/npm-vuln-scanner.git
Project-URL: Issues, https://github.com/mjbommar/npm-vuln-scanner/issues
Keywords: npm,security,vulnerability,scanner,supply-chain,nodejs,dependencies,chalk,debug
Classifier: Development Status :: 4 - Beta
Classifier: Environment :: Console
Classifier: Intended Audience :: Developers
Classifier: Intended Audience :: System Administrators
Classifier: Operating System :: OS Independent
Classifier: Programming Language :: Python :: 3
Classifier: Programming Language :: Python :: 3.6
Classifier: Programming Language :: Python :: 3.7
Classifier: Programming Language :: Python :: 3.8
Classifier: Programming Language :: Python :: 3.9
Classifier: Programming Language :: Python :: 3.10
Classifier: Programming Language :: Python :: 3.11
Classifier: Programming Language :: Python :: 3.12
Classifier: Topic :: Security
Classifier: Topic :: Software Development :: Quality Assurance
Classifier: Topic :: System :: Systems Administration
Requires-Python: >=3.6
License-File: LICENSE
Dynamic: license-file
